odoo/addons/web_fix_modules_load/README.rst
odoo/addons/web_fix_modules_load/__init__.py
odoo/addons/web_fix_modules_load/__manifest__.py
odoo/addons/web_fix_modules_load/controllers/__init__.py
odoo/addons/web_fix_modules_load/controllers/main.py
odoo/addons/web_fix_modules_load/i18n/web_fix_modules_load.pot
odoo/addons/web_fix_modules_load/models/__init__.py
odoo/addons/web_fix_modules_load/models/ir_module.py
odoo/addons/web_fix_modules_load/models/ir_translation.py
odoo/addons/web_fix_modules_load/readme/CONTRIBUTORS.rst
odoo/addons/web_fix_modules_load/readme/DESCRIPTION.rst
odoo/addons/web_fix_modules_load/static/description/icon.png
odoo/addons/web_fix_modules_load/static/description/index.html
odoo/addons/web_fix_modules_load/static/src/js/session.js
odoo/addons/web_fix_modules_load/templates/assets.xml
odoo14_addon_web_fix_modules_load-14.0.1.0.1.dev2.dist-info/METADATA
odoo14_addon_web_fix_modules_load-14.0.1.0.1.dev2.dist-info/WHEEL
odoo14_addon_web_fix_modules_load-14.0.1.0.1.dev2.dist-info/top_level.txt
odoo14_addon_web_fix_modules_load-14.0.1.0.1.dev2.dist-info/RECORD
